{
  "JIJNDLLPCHO": [
    {
      "BBICBMCKMOO": 1970102,
      "JCJNPJKPLJO": 0,
      "OKFJJEHFALE": 197010203,
      "ICODADFFAOD": 1970102
    },
    {
      "BBICBMCKMOO": 1970103,
      "JCJNPJKPLJO": 0,
      "OKFJJEHFALE": 197010300,
      "ICODADFFAOD": 1970103
    },
    {
      "BBICBMCKMOO": 1970104,
      "JCJNPJKPLJO": 0,
      "OKFJJEHFALE": 197010401,
      "ICODADFFAOD": 1970104
    },
    {
      "BBICBMCKMOO": 1970105,
      "JCJNPJKPLJO": 0,
      "OKFJJEHFALE": 197010500,
      "ICODADFFAOD": 1970105
    },
    {
      "BBICBMCKMOO": 1228201001,
      "JCJNPJKPLJO": 0,
      "OKFJJEHFALE": 0,
      "ICODADFFAOD": 1228201001
    },
    {
      "BBICBMCKMOO": 1228201002,
      "JCJNPJKPLJO": 0,
      "OKFJJEHFALE": 0,
      "ICODADFFAOD": 1228201002
    },
    {
      "BBICBMCKMOO": 1228201003,
      "JCJNPJKPLJO": 0,
      "OKFJJEHFALE": 0,
      "ICODADFFAOD": 1228201003
    },
    {
      "BBICBMCKMOO": 1228201004,
      "JCJNPJKPLJO": 0,
      "OKFJJEHFALE": 0,
      "ICODADFFAOD": 1228201004
    },
    {
      "BBICBMCKMOO": 1228201005,
      "JCJNPJKPLJO": 0,
      "OKFJJEHFALE": 0,
      "ICODADFFAOD": 1228201005
    },
    {
      "BBICBMCKMOO": 1228201006,
      "JCJNPJKPLJO": 0,
      "OKFJJEHFALE": 0,
      "ICODADFFAOD": 1228201006
    },
    {
      "BBICBMCKMOO": 1228201007,
      "JCJNPJKPLJO": 0,
      "OKFJJEHFALE": 0,
      "ICODADFFAOD": 1228201007
    },
    {
      "BBICBMCKMOO": 1228201008,
      "JCJNPJKPLJO": 0,
      "OKFJJEHFALE": 0,
      "ICODADFFAOD": 1228201008
    },
    {
      "BBICBMCKMOO": 1228201009,
      "JCJNPJKPLJO": 0,
      "OKFJJEHFALE": 0,
      "ICODADFFAOD": 1228201009
    },
    {
      "BBICBMCKMOO": 1228201010,
      "JCJNPJKPLJO": 0,
      "OKFJJEHFALE": 0,
      "ICODADFFAOD": 1228201010
    },
    {
      "BBICBMCKMOO": 1228201011,
      "JCJNPJKPLJO": 0,
      "OKFJJEHFALE": 0,
      "ICODADFFAOD": 1228201011
    },
    {
      "BBICBMCKMOO": 1228201012,
      "JCJNPJKPLJO": 0,
      "OKFJJEHFALE": 0,
      "ICODADFFAOD": 1228201012
    },
    {
      "BBICBMCKMOO": 1228201013,
      "JCJNPJKPLJO": 0,
      "OKFJJEHFALE": 0,
      "ICODADFFAOD": 1228201013
    },
    {
      "BBICBMCKMOO": 1228201014,
      "JCJNPJKPLJO": 0,
      "OKFJJEHFALE": 0,
      "ICODADFFAOD": 1228201014
    },
    {
      "BBICBMCKMOO": 1228201015,
      "JCJNPJKPLJO": 0,
      "OKFJJEHFALE": 0,
      "ICODADFFAOD": 1228201015
    }
  ]
}