{
  "KHHABHLHAFG": [
    {
      "DJIDNEMBKCL": 1,
      "NFFDNKDOBEJ": "LimboClueSystem_CumulateRewardDesc_1",
      "KJMDLJKAJGG": 1,
      "OHHLJKMAKED": "",
      "PCBMFGJCLDA": 105030001,
      "POAKGBGENGG": 10
    },
    {
      "DJIDNEMBKCL": 2,
      "NFFDNKDOBEJ": "LimboClueSystem_CumulateRewardDesc_2",
      "KJMDLJKAJGG": 2,
      "OHHLJKMAKED": "",
      "PCBMFGJCLDA": 105030002,
      "POAKGBGENGG": 20
    },
    {
      "DJIDNEMBKCL": 3,
      "NFFDNKDOBEJ": "LimboClueSystem_CumulateRewardDesc_3",
      "KJMDLJKAJGG": 3,
      "OHHLJKMAKED": "",
      "PCBMFGJCLDA": 105030003,
      "POAKGBGENGG": 30
    },
    {
      "DJIDNEMBKCL": 4,
      "NFFDNKDOBEJ": "LimboClueSystem_CumulateRewardDesc_4",
      "KJMDLJKAJGG": 4,
      "OHHLJKMAKED": "",
      "PCBMFGJCLDA": 105030004,
      "POAKGBGENGG": 40
    },
    {
      "DJIDNEMBKCL": 5,
      "NFFDNKDOBEJ": "LimboClueSystem_CumulateRewardDesc_5",
      "KJMDLJKAJGG": 5,
      "OHHLJKMAKED": "",
      "PCBMFGJCLDA": 105030005,
      "POAKGBGENGG": 50
    },
    {
      "DJIDNEMBKCL": 6,
      "NFFDNKDOBEJ": "LimboClueSystem_CumulateRewardDesc_6",
      "KJMDLJKAJGG": 6,
      "OHHLJKMAKED": "",
      "PCBMFGJCLDA": 105030006,
      "POAKGBGENGG": 60
    },
    {
      "DJIDNEMBKCL": 7,
      "NFFDNKDOBEJ": "LimboClueSystem_CumulateRewardDesc_7",
      "KJMDLJKAJGG": 7,
      "OHHLJKMAKED": "",
      "PCBMFGJCLDA": 105030007,
      "POAKGBGENGG": 70
    },
    {
      "DJIDNEMBKCL": 8,
      "NFFDNKDOBEJ": "LimboClueSystem_CumulateRewardDesc_8",
      "KJMDLJKAJGG": 8,
      "OHHLJKMAKED": "",
      "PCBMFGJCLDA": 105030008,
      "POAKGBGENGG": 80
    },
    {
      "DJIDNEMBKCL": 9,
      "NFFDNKDOBEJ": "LimboClueSystem_CumulateRewardDesc_9",
      "KJMDLJKAJGG": 9,
      "OHHLJKMAKED": "",
      "PCBMFGJCLDA": 105030009,
      "POAKGBGENGG": 90
    },
    {
      "DJIDNEMBKCL": 10,
      "NFFDNKDOBEJ": "LimboClueSystem_CumulateRewardDesc_10",
      "KJMDLJKAJGG": 10,
      "OHHLJKMAKED": "",
      "PCBMFGJCLDA": 105030010,
      "POAKGBGENGG": 100
    },
    {
      "DJIDNEMBKCL": 11,
      "NFFDNKDOBEJ": "LimboClueSystem_CumulateRewardDesc_11",
      "KJMDLJKAJGG": 11,
      "OHHLJKMAKED": "",
      "PCBMFGJCLDA": 105030011,
      "POAKGBGENGG": 110
    },
    {
      "DJIDNEMBKCL": 12,
      "NFFDNKDOBEJ": "LimboClueSystem_CumulateRewardDesc_12",
      "KJMDLJKAJGG": 12,
      "OHHLJKMAKED": "",
      "PCBMFGJCLDA": 105030012,
      "POAKGBGENGG": 120
    }
  ]
}