{
  "JIJNDLLPCHO": [
    {
      "FAMENNMCDAI": 1,
      "DMNAKKCJLMK": "RemandSubTab_01",
      "FHEBHOLDIOI": 0,
      "LLCNHHCCDHH": 1,
      "BLAIMOOFKDC": 1003002,
      "HKAGACKIGDO": false,
      "DPAKMKDAJIC": "RemandTag_02",
      "AHPDAMEHBNO": "Gift_2000017_name",
      "GMKFMKDFKIM": "RemandGoodsDesc_01",
      "DCKDJJNELOH": "Assets/NapResources/UI/Menus/Widget/ShoppingMall/RecommendationBg/ShoppingMallRecommendationBg01.prefab",
      "ICOGDNPPJNG": null,
      "CEADBHNMPLP": null,
      "LKJOMDPPFMO": 1000,
      "COKKMHGAOFJ": 10000,
      "OEJCJDFGADP": 0
    }
  ]
}