{
  "AbilityMixins": [
    {
      "$type": "AttachStateWithModifierMixin",
      "ConfigList": [
        {
          "AnimatorStateName": "Attack_Normal_01_Charge",
          "FrameCountHigh": 0,
          "FrameCountLow": 0,
          "IsLoop": false,
          "LayerIndex": 0,
          "MaxFrameCountHigh": true,
          "MaxFrameCountLow": false,
          "ModifierNameList": [
            "WeaponTransformModifer_End_L",
            "SpecialEffectModifer_LoopGlow_L"
          ]
        },
        {
          "AnimatorStateName": "Attack_Normal_01_Enhance",
          "FrameCountHigh": 0,
          "FrameCountLow": 0,
          "IsLoop": false,
          "LayerIndex": 0,
          "MaxFrameCountHigh": true,
          "MaxFrameCountLow": false,
          "ModifierNameList": [
            "WeaponTransformModifer_End_L"
          ]
        },
        {
          "AnimatorStateName": "Attack_Normal_02_Charge",
          "FrameCountHigh": 0,
          "FrameCountLow": 0,
          "IsLoop": false,
          "LayerIndex": 0,
          "MaxFrameCountHigh": true,
          "MaxFrameCountLow": false,
          "ModifierNameList": [
            "WeaponTransformModifer_End_L",
            "SpecialEffectModifer_LoopGlow_L"
          ]
        },
        {
          "AnimatorStateName": "Attack_Normal_02_Enhance",
          "FrameCountHigh": 0,
          "FrameCountLow": 0,
          "IsLoop": false,
          "LayerIndex": 0,
          "MaxFrameCountHigh": true,
          "MaxFrameCountLow": false,
          "ModifierNameList": [
            "WeaponTransformModifer_End_L"
          ]
        },
        {
          "AnimatorStateName": "Attack_Normal_03_Charge",
          "FrameCountHigh": 0,
          "FrameCountLow": 0,
          "IsLoop": false,
          "LayerIndex": 0,
          "MaxFrameCountHigh": true,
          "MaxFrameCountLow": false,
          "ModifierNameList": [
            "WeaponTransformModifer_End_L",
            "SpecialEffectModifer_LoopGlow_L"
          ]
        },
        {
          "AnimatorStateName": "Attack_Normal_03_Enhance",
          "FrameCountHigh": 0,
          "FrameCountLow": 0,
          "IsLoop": false,
          "LayerIndex": 0,
          "MaxFrameCountHigh": true,
          "MaxFrameCountLow": false,
          "ModifierNameList": [
            "WeaponTransformModifer_End_L"
          ]
        },
        {
          "AnimatorStateName": "Attack_Normal_04_Charge",
          "FrameCountHigh": 0,
          "FrameCountLow": 0,
          "IsLoop": false,
          "LayerIndex": 0,
          "MaxFrameCountHigh": true,
          "MaxFrameCountLow": false,
          "ModifierNameList": [
            "WeaponTransformModifer_End_L",
            "SpecialEffectModifer_LoopGlow_L"
          ]
        },
        {
          "AnimatorStateName": "Attack_Normal_04_Enhance",
          "FrameCountHigh": 0,
          "FrameCountLow": 0,
          "IsLoop": false,
          "LayerIndex": 0,
          "MaxFrameCountHigh": true,
          "MaxFrameCountLow": false,
          "ModifierNameList": [
            "WeaponTransformModifer_End_L"
          ]
        },
        {
          "AnimatorStateName": "Attack_Normal_05_Charge",
          "FrameCountHigh": 0,
          "FrameCountLow": 0,
          "IsLoop": false,
          "LayerIndex": 0,
          "MaxFrameCountHigh": true,
          "MaxFrameCountLow": false,
          "ModifierNameList": [
            "WeaponTransformModifer_End_L",
            "SpecialEffectModifer_LoopGlow_L"
          ]
        },
        {
          "AnimatorStateName": "Attack_Normal_05_Enhance_01",
          "FrameCountHigh": 0,
          "FrameCountLow": 0,
          "IsLoop": false,
          "LayerIndex": 0,
          "MaxFrameCountHigh": true,
          "MaxFrameCountLow": false,
          "ModifierNameList": [
            "WeaponTransformModifer_End_L"
          ]
        },
        {
          "AnimatorStateName": "Attack_Normal_05_Enhance_02",
          "FrameCountHigh": 0,
          "FrameCountLow": 0,
          "IsLoop": false,
          "LayerIndex": 0,
          "MaxFrameCountHigh": true,
          "MaxFrameCountLow": false,
          "ModifierNameList": [
            "WeaponTransformModifer_End_L"
          ]
        },
        {
          "AnimatorStateName": "Attack_Counter",
          "FrameCountHigh": 0,
          "FrameCountLow": 0,
          "IsLoop": false,
          "LayerIndex": 0,
          "MaxFrameCountHigh": true,
          "MaxFrameCountLow": false,
          "ModifierNameList": [
            "WeaponTransformModifer_End_L"
          ]
        },
        {
          "AnimatorStateName": "Attack_BeHitAid",
          "FrameCountHigh": 0,
          "FrameCountLow": 0,
          "IsLoop": false,
          "LayerIndex": 0,
          "MaxFrameCountHigh": true,
          "MaxFrameCountLow": false,
          "ModifierNameList": [
            "WeaponTransformModifer_End_L"
          ]
        },
        {
          "AnimatorStateName": "Attack_Branch_01_Start",
          "FrameCountHigh": 0,
          "FrameCountLow": 0,
          "IsLoop": false,
          "LayerIndex": 0,
          "MaxFrameCountHigh": true,
          "MaxFrameCountLow": false,
          "ModifierNameList": [
            "WeaponTransformModifer_End_L"
          ]
        },
        {
          "AnimatorStateName": "Attack_Branch_01_Attack",
          "FrameCountHigh": 0,
          "FrameCountLow": 0,
          "IsLoop": false,
          "LayerIndex": 0,
          "MaxFrameCountHigh": true,
          "MaxFrameCountLow": false,
          "ModifierNameList": [
            "WeaponTransformModifer_End_L"
          ]
        },
        {
          "AnimatorStateName": "Attack_Branch_01_Charge",
          "FrameCountHigh": 0,
          "FrameCountLow": 0,
          "IsLoop": false,
          "LayerIndex": 0,
          "MaxFrameCountHigh": true,
          "MaxFrameCountLow": false,
          "ModifierNameList": [
            "WeaponTransformModifer_End_L",
            "SpecialEffectModifer_LoopGlow_L"
          ]
        },
        {
          "AnimatorStateName": "Attack_Branch_01_ChargeAttack_01",
          "FrameCountHigh": 0,
          "FrameCountLow": 0,
          "IsLoop": false,
          "LayerIndex": 0,
          "MaxFrameCountHigh": true,
          "MaxFrameCountLow": false,
          "ModifierNameList": [
            "WeaponTransformModifer_End_L"
          ]
        },
        {
          "AnimatorStateName": "Attack_Branch_01_ChargeAttack_02",
          "FrameCountHigh": 0,
          "FrameCountLow": 0,
          "IsLoop": false,
          "LayerIndex": 0,
          "MaxFrameCountHigh": true,
          "MaxFrameCountLow": false,
          "ModifierNameList": [
            "WeaponTransformModifer_End_L"
          ]
        },
        {
          "AnimatorStateName": "Attack_Branch_02_Start",
          "FrameCountHigh": 0,
          "FrameCountLow": 0,
          "IsLoop": false,
          "LayerIndex": 0,
          "MaxFrameCountHigh": true,
          "MaxFrameCountLow": false,
          "ModifierNameList": [
            "WeaponTransformModifer_End_L"
          ]
        },
        {
          "AnimatorStateName": "Attack_Branch_02_Attack",
          "FrameCountHigh": 0,
          "FrameCountLow": 0,
          "IsLoop": false,
          "LayerIndex": 0,
          "MaxFrameCountHigh": true,
          "MaxFrameCountLow": false,
          "ModifierNameList": [
            "WeaponTransformModifer_End_L"
          ]
        },
        {
          "AnimatorStateName": "Attack_Branch_02_Charge",
          "FrameCountHigh": 0,
          "FrameCountLow": 0,
          "IsLoop": false,
          "LayerIndex": 0,
          "MaxFrameCountHigh": true,
          "MaxFrameCountLow": false,
          "ModifierNameList": [
            "WeaponTransformModifer_End_L",
            "SpecialEffectModifer_LoopGlow_L"
          ]
        },
        {
          "AnimatorStateName": "Attack_Branch_02_ChargeAttack_01",
          "FrameCountHigh": 0,
          "FrameCountLow": 0,
          "IsLoop": false,
          "LayerIndex": 0,
          "MaxFrameCountHigh": true,
          "MaxFrameCountLow": false,
          "ModifierNameList": [
            "WeaponTransformModifer_End_L"
          ]
        },
        {
          "AnimatorStateName": "Attack_Branch_02_ChargeAttack_02",
          "FrameCountHigh": 0,
          "FrameCountLow": 0,
          "IsLoop": false,
          "LayerIndex": 0,
          "MaxFrameCountHigh": true,
          "MaxFrameCountLow": false,
          "ModifierNameList": [
            "WeaponTransformModifer_End_L"
          ]
        },
        {
          "AnimatorStateName": "SwitchIn_Attack",
          "FrameCountHigh": 0,
          "FrameCountLow": 0,
          "IsLoop": false,
          "LayerIndex": 0,
          "MaxFrameCountHigh": true,
          "MaxFrameCountLow": false,
          "ModifierNameList": [
            "WeaponTransformModifer_End_L"
          ]
        },
        {
          "AnimatorStateName": "SwitchIn_Attack_Ex",
          "FrameCountHigh": 0,
          "FrameCountLow": 0,
          "IsLoop": false,
          "LayerIndex": 0,
          "MaxFrameCountHigh": true,
          "MaxFrameCountLow": false,
          "ModifierNameList": [
            "WeaponTransformModifer_End_L"
          ]
        },
        {
          "AnimatorStateName": "Attack_ParryAid_L",
          "FrameCountHigh": 12,
          "FrameCountLow": 0,
          "IsLoop": false,
          "LayerIndex": 0,
          "MaxFrameCountHigh": false,
          "MaxFrameCountLow": false,
          "ModifierNameList": [
            "WeaponTransformModifer_End_L"
          ]
        },
        {
          "AnimatorStateName": "Attack_ParryAid_H",
          "FrameCountHigh": 32,
          "FrameCountLow": 0,
          "IsLoop": false,
          "LayerIndex": 0,
          "MaxFrameCountHigh": false,
          "MaxFrameCountLow": false,
          "ModifierNameList": [
            "WeaponTransformModifer_End_L"
          ]
        },
        {
          "AnimatorStateName": "Attack_ParryAid_H_Loop",
          "FrameCountHigh": 27,
          "FrameCountLow": 0,
          "IsLoop": false,
          "LayerIndex": 0,
          "MaxFrameCountHigh": false,
          "MaxFrameCountLow": false,
          "ModifierNameList": [
            "WeaponTransformModifer_End_L"
          ]
        },
        {
          "AnimatorStateName": "Attack_AssaultAid",
          "FrameCountHigh": 90,
          "FrameCountLow": 0,
          "IsLoop": false,
          "LayerIndex": 0,
          "MaxFrameCountHigh": false,
          "MaxFrameCountLow": false,
          "ModifierNameList": [
            "WeaponTransformModifer_End_L"
          ]
        },
        {
          "AnimatorStateName": "Attack_Normal_01_Charge",
          "FrameCountHigh": 0,
          "FrameCountLow": 0,
          "IsLoop": false,
          "LayerIndex": 0,
          "MaxFrameCountHigh": true,
          "MaxFrameCountLow": false,
          "ModifierNameList": [
            "WeaponTransformModifer_End_R",
            "SpecialEffectModifer_LoopGlow_R"
          ]
        },
        {
          "AnimatorStateName": "Attack_Normal_01_Enhance",
          "FrameCountHigh": 0,
          "FrameCountLow": 0,
          "IsLoop": false,
          "LayerIndex": 0,
          "MaxFrameCountHigh": true,
          "MaxFrameCountLow": false,
          "ModifierNameList": [
            "WeaponTransformModifer_End_R"
          ]
        },
        {
          "AnimatorStateName": "Attack_Normal_02_Charge",
          "FrameCountHigh": 0,
          "FrameCountLow": 0,
          "IsLoop": false,
          "LayerIndex": 0,
          "MaxFrameCountHigh": true,
          "MaxFrameCountLow": false,
          "ModifierNameList": [
            "WeaponTransformModifer_End_R",
            "SpecialEffectModifer_LoopGlow_R"
          ]
        },
        {
          "AnimatorStateName": "Attack_Normal_02_Enhance",
          "FrameCountHigh": 0,
          "FrameCountLow": 0,
          "IsLoop": false,
          "LayerIndex": 0,
          "MaxFrameCountHigh": true,
          "MaxFrameCountLow": false,
          "ModifierNameList": [
            "WeaponTransformModifer_End_R"
          ]
        },
        {
          "AnimatorStateName": "Attack_Normal_03_Charge",
          "FrameCountHigh": 0,
          "FrameCountLow": 0,
          "IsLoop": false,
          "LayerIndex": 0,
          "MaxFrameCountHigh": true,
          "MaxFrameCountLow": false,
          "ModifierNameList": [
            "WeaponTransformModifer_End_R"
          ]
        },
        {
          "AnimatorStateName": "Attack_Normal_03_Enhance",
          "FrameCountHigh": 0,
          "FrameCountLow": 0,
          "IsLoop": false,
          "LayerIndex": 0,
          "MaxFrameCountHigh": true,
          "MaxFrameCountLow": false,
          "ModifierNameList": [
            "WeaponTransformModifer_End_R"
          ]
        },
        {
          "AnimatorStateName": "Attack_Normal_05_Charge",
          "FrameCountHigh": 0,
          "FrameCountLow": 0,
          "IsLoop": false,
          "LayerIndex": 0,
          "MaxFrameCountHigh": true,
          "MaxFrameCountLow": false,
          "ModifierNameList": [
            "WeaponTransformModifer_End_R",
            "SpecialEffectModifer_LoopGlow_R"
          ]
        },
        {
          "AnimatorStateName": "Attack_Normal_05_Enhance_01",
          "FrameCountHigh": 0,
          "FrameCountLow": 0,
          "IsLoop": false,
          "LayerIndex": 0,
          "MaxFrameCountHigh": true,
          "MaxFrameCountLow": false,
          "ModifierNameList": [
            "WeaponTransformModifer_End_R"
          ]
        },
        {
          "AnimatorStateName": "Attack_Normal_05_Enhance_02",
          "FrameCountHigh": 0,
          "FrameCountLow": 0,
          "IsLoop": false,
          "LayerIndex": 0,
          "MaxFrameCountHigh": true,
          "MaxFrameCountLow": false,
          "ModifierNameList": [
            "WeaponTransformModifer_End_R"
          ]
        },
        {
          "AnimatorStateName": "Attack_Counter",
          "FrameCountHigh": 0,
          "FrameCountLow": 0,
          "IsLoop": false,
          "LayerIndex": 0,
          "MaxFrameCountHigh": true,
          "MaxFrameCountLow": false,
          "ModifierNameList": [
            "WeaponTransformModifer_End_R"
          ]
        },
        {
          "AnimatorStateName": "Attack_BeHitAid",
          "FrameCountHigh": 0,
          "FrameCountLow": 0,
          "IsLoop": false,
          "LayerIndex": 0,
          "MaxFrameCountHigh": true,
          "MaxFrameCountLow": false,
          "ModifierNameList": [
            "WeaponTransformModifer_End_R"
          ]
        },
        {
          "AnimatorStateName": "Attack_Branch_01_Start",
          "FrameCountHigh": 0,
          "FrameCountLow": 0,
          "IsLoop": false,
          "LayerIndex": 0,
          "MaxFrameCountHigh": true,
          "MaxFrameCountLow": false,
          "ModifierNameList": [
            "WeaponTransformModifer_End_R"
          ]
        },
        {
          "AnimatorStateName": "Attack_Branch_01_Attack",
          "FrameCountHigh": 0,
          "FrameCountLow": 0,
          "IsLoop": false,
          "LayerIndex": 0,
          "MaxFrameCountHigh": true,
          "MaxFrameCountLow": false,
          "ModifierNameList": [
            "WeaponTransformModifer_End_R"
          ]
        },
        {
          "AnimatorStateName": "Attack_Branch_01_Charge",
          "FrameCountHigh": 0,
          "FrameCountLow": 0,
          "IsLoop": false,
          "LayerIndex": 0,
          "MaxFrameCountHigh": true,
          "MaxFrameCountLow": false,
          "ModifierNameList": [
            "WeaponTransformModifer_End_R",
            "SpecialEffectModifer_LoopGlow_R"
          ]
        },
        {
          "AnimatorStateName": "Attack_Branch_01_ChargeAttack_01",
          "FrameCountHigh": 0,
          "FrameCountLow": 0,
          "IsLoop": false,
          "LayerIndex": 0,
          "MaxFrameCountHigh": true,
          "MaxFrameCountLow": false,
          "ModifierNameList": [
            "WeaponTransformModifer_End_R"
          ]
        },
        {
          "AnimatorStateName": "Attack_Branch_01_ChargeAttack_02",
          "FrameCountHigh": 0,
          "FrameCountLow": 0,
          "IsLoop": false,
          "LayerIndex": 0,
          "MaxFrameCountHigh": true,
          "MaxFrameCountLow": false,
          "ModifierNameList": [
            "WeaponTransformModifer_End_R"
          ]
        },
        {
          "AnimatorStateName": "Attack_Branch_02_Start",
          "FrameCountHigh": 0,
          "FrameCountLow": 0,
          "IsLoop": false,
          "LayerIndex": 0,
          "MaxFrameCountHigh": true,
          "MaxFrameCountLow": false,
          "ModifierNameList": [
            "WeaponTransformModifer_End_R"
          ]
        },
        {
          "AnimatorStateName": "Attack_Branch_02_Attack",
          "FrameCountHigh": 0,
          "FrameCountLow": 0,
          "IsLoop": false,
          "LayerIndex": 0,
          "MaxFrameCountHigh": true,
          "MaxFrameCountLow": false,
          "ModifierNameList": [
            "WeaponTransformModifer_End_R"
          ]
        },
        {
          "AnimatorStateName": "Attack_Branch_02_Charge",
          "FrameCountHigh": 0,
          "FrameCountLow": 0,
          "IsLoop": false,
          "LayerIndex": 0,
          "MaxFrameCountHigh": true,
          "MaxFrameCountLow": false,
          "ModifierNameList": [
            "WeaponTransformModifer_End_R",
            "SpecialEffectModifer_LoopGlow_R"
          ]
        },
        {
          "AnimatorStateName": "Attack_Branch_02_ChargeAttack_01",
          "FrameCountHigh": 0,
          "FrameCountLow": 0,
          "IsLoop": false,
          "LayerIndex": 0,
          "MaxFrameCountHigh": true,
          "MaxFrameCountLow": false,
          "ModifierNameList": [
            "WeaponTransformModifer_End_R"
          ]
        },
        {
          "AnimatorStateName": "Attack_Branch_02_ChargeAttack_02",
          "FrameCountHigh": 0,
          "FrameCountLow": 0,
          "IsLoop": false,
          "LayerIndex": 0,
          "MaxFrameCountHigh": true,
          "MaxFrameCountLow": false,
          "ModifierNameList": [
            "WeaponTransformModifer_End_R"
          ]
        },
        {
          "AnimatorStateName": "SwitchIn_Attack",
          "FrameCountHigh": 0,
          "FrameCountLow": 0,
          "IsLoop": false,
          "LayerIndex": 0,
          "MaxFrameCountHigh": true,
          "MaxFrameCountLow": false,
          "ModifierNameList": [
            "WeaponTransformModifer_End_R"
          ]
        },
        {
          "AnimatorStateName": "SwitchIn_Attack_Ex",
          "FrameCountHigh": 0,
          "FrameCountLow": 0,
          "IsLoop": false,
          "LayerIndex": 0,
          "MaxFrameCountHigh": true,
          "MaxFrameCountLow": false,
          "ModifierNameList": [
            "WeaponTransformModifer_End_R"
          ]
        },
        {
          "AnimatorStateName": "Attack_ParryAid_L",
          "FrameCountHigh": 12,
          "FrameCountLow": 0,
          "IsLoop": false,
          "LayerIndex": 0,
          "MaxFrameCountHigh": false,
          "MaxFrameCountLow": false,
          "ModifierNameList": [
            "WeaponTransformModifer_End_R"
          ]
        },
        {
          "AnimatorStateName": "Attack_ParryAid_H",
          "FrameCountHigh": 32,
          "FrameCountLow": 0,
          "IsLoop": false,
          "LayerIndex": 0,
          "MaxFrameCountHigh": false,
          "MaxFrameCountLow": false,
          "ModifierNameList": [
            "WeaponTransformModifer_End_R"
          ]
        },
        {
          "AnimatorStateName": "Attack_ParryAid_H_Loop",
          "FrameCountHigh": 27,
          "FrameCountLow": 0,
          "IsLoop": false,
          "LayerIndex": 0,
          "MaxFrameCountHigh": false,
          "MaxFrameCountLow": false,
          "ModifierNameList": [
            "WeaponTransformModifer_End_R"
          ]
        }
      ]
    }
  ],
  "AbilityName": "Lycaon_WeaponTransform",
  "AbilityStacking": "Unique",
  "Modifiers": {
    "SpecialEffectModifer_01_L": {
      "Duration": -1,
      "IgnoreTimeScale": false,
      "ModifierStacking": "Unique",
      "OnAdded": [
        {
          "$type": "AttachEffect",
          "AttachEffectPosRot": {
            "CoordsOption": "ReferTarget",
            "Offset": {
              "AngleOffset": {
                "x": 0.0,
                "y": 0.0,
                "z": 0.0
              },
              "IsUseRotationXZ": true,
              "IsUseRotationY": true,
              "PositionOffset": {
                "x": 0.0,
                "y": 0.0,
                "z": 0.0
              }
            },
            "TargetOption": {
              "$type": "ConfigPosRotReferTarget",
              "AttachPoint": "PT_L_WeaponD",
              "IsUseAttachPointPos": true,
              "IsUseAttachPointRotation": true,
              "OffsetReferTarget": "Self"
            }
          },
          "EffectPattern": "Eff_Lycaon_WeaponTransform_01_Loop_L",
          "Target": "Self"
        }
      ]
    },
    "SpecialEffectModifer_01_R": {
      "Duration": -1,
      "IgnoreTimeScale": false,
      "ModifierStacking": "Unique",
      "OnAdded": [
        {
          "$type": "AttachEffect",
          "AttachEffectPosRot": {
            "CoordsOption": "ReferTarget",
            "Offset": {
              "AngleOffset": {
                "x": 0.0,
                "y": 0.0,
                "z": 0.0
              },
              "IsUseRotationXZ": true,
              "IsUseRotationY": true,
              "PositionOffset": {
                "x": 0.0,
                "y": 0.0,
                "z": 0.0
              }
            },
            "TargetOption": {
              "$type": "ConfigPosRotReferTarget",
              "AttachPoint": "PT_R_WeaponD",
              "IsUseAttachPointPos": true,
              "IsUseAttachPointRotation": true,
              "OffsetReferTarget": "Self"
            }
          },
          "EffectPattern": "Eff_Lycaon_WeaponTransform_01_Loop_R",
          "Target": "Self"
        }
      ]
    },
    "SpecialEffectModifer_02_L": {
      "Duration": -1,
      "IgnoreTimeScale": false,
      "ModifierStacking": "Unique",
      "OnAdded": [
        {
          "$type": "AttachEffect",
          "AttachEffectPosRot": {
            "CoordsOption": "ReferTarget",
            "Offset": {
              "AngleOffset": {
                "x": 0.0,
                "y": 0.0,
                "z": 0.0
              },
              "IsUseRotationXZ": true,
              "IsUseRotationY": true,
              "PositionOffset": {
                "x": 0.0,
                "y": 0.0,
                "z": 0.0
              }
            },
            "TargetOption": {
              "$type": "ConfigPosRotReferTarget",
              "AttachPoint": "PT_L_WeaponD",
              "IsUseAttachPointPos": true,
              "IsUseAttachPointRotation": true,
              "OffsetReferTarget": "Self"
            }
          },
          "EffectPattern": "Eff_Lycaon_WeaponTransform_02_Loop",
          "Target": "Self"
        },
        {
          "$type": "AttachEffect",
          "AttachEffectPosRot": {
            "CoordsOption": "ReferTarget",
            "Offset": {
              "AngleOffset": {
                "x": 0.0,
                "y": 0.0,
                "z": 0.0
              },
              "IsUseRotationXZ": true,
              "IsUseRotationY": true,
              "PositionOffset": {
                "x": 0.0,
                "y": 0.0,
                "z": 0.0
              }
            },
            "TargetOption": {
              "$type": "ConfigPosRotReferTarget",
              "AttachPoint": "PT_L_WeaponD",
              "IsUseAttachPointPos": true,
              "IsUseAttachPointRotation": true,
              "OffsetReferTarget": "Self"
            }
          },
          "EffectPattern": "Eff_Lycaon_WeaponTransform_03_Loop",
          "Target": "Self"
        }
      ]
    },
    "SpecialEffectModifer_02_R": {
      "Duration": -1,
      "IgnoreTimeScale": false,
      "ModifierStacking": "Unique",
      "OnAdded": [
        {
          "$type": "AttachEffect",
          "AttachEffectPosRot": {
            "CoordsOption": "ReferTarget",
            "Offset": {
              "AngleOffset": {
                "x": 0.0,
                "y": 0.0,
                "z": 0.0
              },
              "IsUseRotationXZ": true,
              "IsUseRotationY": true,
              "PositionOffset": {
                "x": 0.0,
                "y": 0.0,
                "z": 0.0
              }
            },
            "TargetOption": {
              "$type": "ConfigPosRotReferTarget",
              "AttachPoint": "PT_R_WeaponD",
              "IsUseAttachPointPos": true,
              "IsUseAttachPointRotation": true,
              "OffsetReferTarget": "Self"
            }
          },
          "EffectPattern": "Eff_Lycaon_WeaponTransform_02_Loop",
          "Target": "Self"
        },
        {
          "$type": "AttachEffect",
          "AttachEffectPosRot": {
            "CoordsOption": "ReferTarget",
            "Offset": {
              "AngleOffset": {
                "x": 0.0,
                "y": 0.0,
                "z": 0.0
              },
              "IsUseRotationXZ": true,
              "IsUseRotationY": true,
              "PositionOffset": {
                "x": 0.0,
                "y": 0.0,
                "z": 0.0
              }
            },
            "TargetOption": {
              "$type": "ConfigPosRotReferTarget",
              "AttachPoint": "PT_R_WeaponD",
              "IsUseAttachPointPos": true,
              "IsUseAttachPointRotation": true,
              "OffsetReferTarget": "Self"
            }
          },
          "EffectPattern": "Eff_Lycaon_WeaponTransform_03_Loop",
          "Target": "Self"
        }
      ]
    },
    "SpecialEffectModifer_LoopGlow_L": {
      "Duration": -1,
      "IgnoreTimeScale": false,
      "ModifierStacking": "Unique",
      "OnAdded": [
        {
          "$type": "AttachEffect",
          "AttachEffectPosRot": {
            "CoordsOption": "ReferTarget",
            "Offset": {
              "AngleOffset": {
                "x": 0.0,
                "y": 0.0,
                "z": 0.0
              },
              "IsUseRotationXZ": true,
              "IsUseRotationY": true,
              "PositionOffset": {
                "x": 0.0,
                "y": 0.0,
                "z": 0.0
              }
            },
            "TargetOption": {
              "$type": "ConfigPosRotReferTarget",
              "AttachPoint": "PT_L_WeaponD",
              "IsUseAttachPointPos": true,
              "IsUseAttachPointRotation": true,
              "OffsetReferTarget": "Self"
            }
          },
          "EffectPattern": "Eff_Lycaon_WeaponTransform_01_LoopGlow",
          "Target": "Self"
        }
      ]
    },
    "SpecialEffectModifer_LoopGlow_R": {
      "Duration": -1,
      "IgnoreTimeScale": false,
      "ModifierStacking": "Unique",
      "OnAdded": [
        {
          "$type": "AttachEffect",
          "AttachEffectPosRot": {
            "CoordsOption": "ReferTarget",
            "Offset": {
              "AngleOffset": {
                "x": 0.0,
                "y": 0.0,
                "z": 0.0
              },
              "IsUseRotationXZ": true,
              "IsUseRotationY": true,
              "PositionOffset": {
                "x": 0.0,
                "y": 0.0,
                "z": 0.0
              }
            },
            "TargetOption": {
              "$type": "ConfigPosRotReferTarget",
              "AttachPoint": "PT_R_WeaponD",
              "IsUseAttachPointPos": true,
              "IsUseAttachPointRotation": true,
              "OffsetReferTarget": "Self"
            }
          },
          "EffectPattern": "Eff_Lycaon_WeaponTransform_01_LoopGlow",
          "Target": "Self"
        }
      ]
    },
    "WeaponTransformModifer_End_L": {
      "Duration": -1,
      "IgnoreTimeScale": false,
      "ModifierStacking": "Unique",
      "OnRemoved": [
        {
          "$type": "SetAnimCtrlerParamAction",
          "BoolVal": true,
          "ParamName": "Trigger_WeaponTransform_End_L",
          "ParamType": 1,
          "Target": "Self"
        },
        {
          "$type": "RemoveModifier",
          "ModifierName": "SpecialEffectModifer_01_L",
          "Target": "Self"
        },
        {
          "$type": "RemoveModifier",
          "ModifierName": "SpecialEffectModifer_02_L",
          "Target": "Self"
        }
      ]
    },
    "WeaponTransformModifer_End_R": {
      "Duration": -1,
      "IgnoreTimeScale": false,
      "ModifierStacking": "Unique",
      "OnRemoved": [
        {
          "$type": "SetAnimCtrlerParamAction",
          "BoolVal": true,
          "ParamName": "Trigger_WeaponTransform_End_R",
          "ParamType": 1,
          "Target": "Self"
        },
        {
          "$type": "RemoveModifier",
          "ModifierName": "SpecialEffectModifer_01_R",
          "Target": "Self"
        },
        {
          "$type": "RemoveModifier",
          "ModifierName": "SpecialEffectModifer_02_R",
          "Target": "Self"
        }
      ]
    },
    "WeaponTransformModifer_Start_01_L": {
      "Duration": 0.1,
      "IgnoreTimeScale": false,
      "ModifierStacking": "MultipleRefresh",
      "OnAdded": [
        {
          "$type": "SetAnimCtrlerParamAction",
          "BoolVal": true,
          "ParamName": "Trigger_WeaponTransform_01_L",
          "ParamType": 1,
          "Target": "Self"
        },
        {
          "$type": "SetAnimCtrlerParamAction",
          "BoolVal": true,
          "ParamName": "Bool_IsEnhanced_01",
          "ParamType": 2,
          "Target": "Self"
        },
        {
          "$type": "ApplyModifier",
          "ModifierName": "SpecialEffectModifer_01_L",
          "Target": "Self"
        },
        {
          "$type": "FireEffect",
          "EffectPattern": "Eff_Lycaon_WeaponTransform_01_Burst",
          "FireEffectPosRot": {
            "CoordsOption": "ReferTarget",
            "NeedRaycastGround": false,
            "Offset": {
              "AngleOffset": {
                "x": 0.0,
                "y": 0.0,
                "z": 0.0
              },
              "IsUseRotationXZ": true,
              "IsUseRotationY": true,
              "PositionOffset": {
                "x": 0.0,
                "y": 0.0,
                "z": 0.0
              }
            },
            "TargetOption": {
              "$type": "ConfigPosRotReferTarget",
              "AttachPoint": "PT_L_WeaponD",
              "IsUseAttachPointPos": true,
              "IsUseAttachPointRotation": true,
              "OffsetReferTarget": "Self"
            }
          },
          "Target": "Self"
        }
      ]
    },
    "WeaponTransformModifer_Start_01_R": {
      "Duration": 0.1,
      "IgnoreTimeScale": false,
      "ModifierStacking": "MultipleRefresh",
      "OnAdded": [
        {
          "$type": "SetAnimCtrlerParamAction",
          "BoolVal": true,
          "ParamName": "Trigger_WeaponTransform_01_R",
          "ParamType": 1,
          "Target": "Self"
        },
        {
          "$type": "SetAnimCtrlerParamAction",
          "BoolVal": true,
          "ParamName": "Bool_IsEnhanced_01",
          "ParamType": 2,
          "Target": "Self"
        },
        {
          "$type": "ApplyModifier",
          "ModifierName": "SpecialEffectModifer_01_R",
          "Target": "Self"
        },
        {
          "$type": "FireEffect",
          "EffectPattern": "Eff_Lycaon_WeaponTransform_01_Burst",
          "FireEffectPosRot": {
            "CoordsOption": "ReferTarget",
            "NeedRaycastGround": false,
            "Offset": {
              "AngleOffset": {
                "x": 0.0,
                "y": 0.0,
                "z": 0.0
              },
              "IsUseRotationXZ": true,
              "IsUseRotationY": true,
              "PositionOffset": {
                "x": 0.0,
                "y": 0.0,
                "z": 0.0
              }
            },
            "TargetOption": {
              "$type": "ConfigPosRotReferTarget",
              "AttachPoint": "PT_R_WeaponD",
              "IsUseAttachPointPos": true,
              "IsUseAttachPointRotation": true,
              "OffsetReferTarget": "Self"
            }
          },
          "Target": "Self"
        }
      ]
    },
    "WeaponTransformModifer_Start_02_L": {
      "Duration": 0.1,
      "IgnoreTimeScale": false,
      "ModifierStacking": "MultipleRefresh",
      "OnAdded": [
        {
          "$type": "ApplyModifier",
          "ModifierName": "WeaponTransformModifer_Start_01_L",
          "Target": "Self"
        },
        {
          "$type": "SetAnimCtrlerParamAction",
          "BoolVal": true,
          "ParamName": "Trigger_WeaponTransform_02_L",
          "ParamType": 1,
          "Target": "Self"
        },
        {
          "$type": "SetAnimCtrlerParamAction",
          "BoolVal": true,
          "ParamName": "Bool_IsEnhanced_02",
          "ParamType": 2,
          "Target": "Self"
        },
        {
          "$type": "ApplyModifier",
          "ModifierName": "SpecialEffectModifer_02_L",
          "Target": "Self"
        },
        {
          "$type": "FireEffect",
          "EffectPattern": "Eff_Lycaon_WeaponTransform_02_Burst",
          "FireEffectPosRot": {
            "CoordsOption": "ReferTarget",
            "NeedRaycastGround": false,
            "Offset": {
              "AngleOffset": {
                "x": 0.0,
                "y": 0.0,
                "z": 0.0
              },
              "IsUseRotationXZ": true,
              "IsUseRotationY": true,
              "PositionOffset": {
                "x": 0.0,
                "y": 0.0,
                "z": 0.0
              }
            },
            "TargetOption": {
              "$type": "ConfigPosRotReferTarget",
              "AttachPoint": "PT_L_WeaponD",
              "IsUseAttachPointPos": true,
              "IsUseAttachPointRotation": true,
              "OffsetReferTarget": "Self"
            }
          },
          "Target": "Self"
        }
      ]
    },
    "WeaponTransformModifer_Start_02_R": {
      "Duration": 0.1,
      "IgnoreTimeScale": false,
      "ModifierStacking": "MultipleRefresh",
      "OnAdded": [
        {
          "$type": "ApplyModifier",
          "ModifierName": "WeaponTransformModifer_Start_01_R",
          "Target": "Self"
        },
        {
          "$type": "SetAnimCtrlerParamAction",
          "BoolVal": true,
          "ParamName": "Trigger_WeaponTransform_02_R",
          "ParamType": 1,
          "Target": "Self"
        },
        {
          "$type": "SetAnimCtrlerParamAction",
          "BoolVal": true,
          "ParamName": "Bool_IsEnhanced_02",
          "ParamType": 2,
          "Target": "Self"
        },
        {
          "$type": "ApplyModifier",
          "ModifierName": "SpecialEffectModifer_02_R",
          "Target": "Self"
        },
        {
          "$type": "FireEffect",
          "EffectPattern": "Eff_Lycaon_WeaponTransform_02_Burst",
          "FireEffectPosRot": {
            "CoordsOption": "ReferTarget",
            "NeedRaycastGround": false,
            "Offset": {
              "AngleOffset": {
                "x": 0.0,
                "y": 0.0,
                "z": 0.0
              },
              "IsUseRotationXZ": true,
              "IsUseRotationY": true,
              "PositionOffset": {
                "x": 0.0,
                "y": 0.0,
                "z": 0.0
              }
            },
            "TargetOption": {
              "$type": "ConfigPosRotReferTarget",
              "AttachPoint": "PT_R_WeaponD",
              "IsUseAttachPointPos": true,
              "IsUseAttachPointRotation": true,
              "OffsetReferTarget": "Self"
            }
          },
          "Target": "Self"
        }
      ]
    }
  },
  "OnAbilityStart": [
    {
      "$type": "ApplyModifier",
      "ModifierName": "WeaponTransformModifer_Start_01_L",
      "Predicates": [
        {
          "$type": "ByIsInZoneTags",
          "Tags": [
            "Trigger_WeaponTransform_01",
            "Trigger_WeaponTransform_L"
          ],
          "Target": "Self"
        }
      ],
      "Target": "Self"
    },
    {
      "$type": "ApplyModifier",
      "ModifierName": "WeaponTransformModifer_Start_01_R",
      "Predicates": [
        {
          "$type": "ByIsInZoneTags",
          "Tags": [
            "Trigger_WeaponTransform_01",
            "Trigger_WeaponTransform_R"
          ],
          "Target": "Self"
        }
      ],
      "Target": "Self"
    },
    {
      "$type": "ApplyModifier",
      "ModifierName": "WeaponTransformModifer_Start_02_L",
      "Predicates": [
        {
          "$type": "ByIsInZoneTags",
          "Tags": [
            "Trigger_WeaponTransform_02",
            "Trigger_WeaponTransform_L"
          ],
          "Target": "Self"
        }
      ],
      "Target": "Self"
    },
    {
      "$type": "ApplyModifier",
      "ModifierName": "WeaponTransformModifer_Start_02_R",
      "Predicates": [
        {
          "$type": "ByIsInZoneTags",
          "Tags": [
            "Trigger_WeaponTransform_02",
            "Trigger_WeaponTransform_R"
          ],
          "Target": "Self"
        }
      ],
      "Target": "Self"
    }
  ]
}