{
  "AbilityMixins": [
    {
      "$type": "AttachStateWithModifierMixin",
      "ConfigList": [
        {
          "AnimatorStateName": "Idle",
          "IsLoop": true,
          "LayerIndex": 0,
          "ModifierNameList": [
            "IdleModifier"
          ],
          "NormalizedTimeHigh": 1.0,
          "NormalizedTimeLow": 0.0
        },
        {
          "AnimatorStateName": "Activating",
          "IsLoop": true,
          "LayerIndex": 0,
          "ModifierNameList": [
            "ActivingModifier"
          ],
          "NormalizedTimeHigh": 1.0,
          "NormalizedTimeLow": 0.0
        },
        {
          "AnimatorStateName": "Attack",
          "IsLoop": true,
          "LayerIndex": 0,
          "ModifierNameList": [
            "AttackModifier"
          ],
          "NormalizedTimeHigh": 1.0,
          "NormalizedTimeLow": 0
        },
        {
          "AnimatorStateName": "CD",
          "IsLoop": false,
          "LayerIndex": 0,
          "ModifierNameList": [
            "CDModifier"
          ],
          "NormalizedTimeHigh": 1.0,
          "NormalizedTimeLow": 0
        },
        {
          "AnimatorStateName": "Close",
          "IsLoop": true,
          "LayerIndex": 0,
          "ModifierNameList": [
            "CloseModifier"
          ],
          "NormalizedTimeHigh": 1.0,
          "NormalizedTimeLow": 0
        }
      ]
    }
  ],
  "AbilityName": "Teller_StateEffect",
  "Modifiers": {
    "ActivingModifier": {
      "Duration": -1,
      "ModifierStacking": "Unique",
      "OnAdded": [
        {
          "$type": "AttachEffect",
          "AttachEffectPosRot": {
            "CoordsOption": "ReferTarget",
            "Offset": {
              "AngleOffset": {
                "x": 0.0,
                "y": 0.0,
                "z": 0.0
              },
              "IsUseRotationXZ": true,
              "IsUseRotationY": true,
              "PositionOffset": {
                "x": 0.0,
                "y": 0.0,
                "z": 0.0
              }
            },
            "TargetOption": {
              "$type": "ConfigPosRotReferTarget",
              "AttachPoint": "BodyPoint",
              "IsUseAttachPointPos": true,
              "IsUseAttachPointRotation": true,
              "OffsetReferTarget": "Self"
            }
          },
          "EffectPattern": "Eff_Device_Teller_Active_01",
          "Target": "Self"
        },
        {
          "$type": "AttachEffect",
          "AttachEffectPosRot": {
            "CoordsOption": "ReferTarget",
            "Offset": {
              "AngleOffset": {
                "x": 0.0,
                "y": 0.0,
                "z": 0.0
              },
              "IsUseRotationXZ": true,
              "IsUseRotationY": true,
              "PositionOffset": {
                "x": 0.0,
                "y": 0.0,
                "z": 0.0
              }
            },
            "TargetOption": {
              "$type": "ConfigPosRotReferTarget",
              "AttachPoint": "RootPoint",
              "IsUseAttachPointPos": true,
              "IsUseAttachPointRotation": true,
              "OffsetReferTarget": "Self"
            }
          },
          "EffectPattern": "Eff_Device_Teller_Active_02",
          "Target": "Self"
        },
        {
          "$type": "FireEffect",
          "EffectPattern": "Eff_Device_Teller_Scan_End",
          "Target": "Self"
        }
      ]
    },
    "AttackModifier": {
      "Duration": -1,
      "ModifierStacking": "Unique",
      "OnAdded": [
        {
          "$type": "AttachEffect",
          "AttachEffectPosRot": {
            "CoordsOption": "ReferTarget",
            "Offset": {
              "AngleOffset": {
                "x": 0.0,
                "y": 0.0,
                "z": 0.0
              },
              "IsUseRotationXZ": true,
              "IsUseRotationY": true,
              "PositionOffset": {
                "x": 0.0,
                "y": 0.0,
                "z": 0.0
              }
            },
            "TargetOption": {
              "$type": "ConfigPosRotReferTarget",
              "AttachPoint": "RootPoint",
              "IsUseAttachPointPos": true,
              "IsUseAttachPointRotation": true,
              "OffsetReferTarget": "Self"
            }
          },
          "EffectPattern": "Eff_Device_Teller_Idle_Red_02",
          "Target": "Self"
        },
        {
          "$type": "AttachEffect",
          "AttachEffectPosRot": {
            "CoordsOption": "ReferTarget",
            "Offset": {
              "AngleOffset": {
                "x": 0.0,
                "y": 0.0,
                "z": 0.0
              },
              "IsUseRotationXZ": true,
              "IsUseRotationY": true,
              "PositionOffset": {
                "x": 0.0,
                "y": 0.0,
                "z": 0.0
              }
            },
            "TargetOption": {
              "$type": "ConfigPosRotReferTarget",
              "AttachPoint": "BodyPoint",
              "IsUseAttachPointPos": true,
              "IsUseAttachPointRotation": true,
              "OffsetReferTarget": "Self"
            }
          },
          "EffectPattern": "Eff_Device_Teller_Idle_Red_01",
          "Target": "Self"
        }
      ]
    },
    "CDModifier": {
      "Duration": -1,
      "ModifierStacking": "Unique",
      "OnAdded": [
        {
          "$type": "LDListenEntityAction",
          "CustomKey": ""
        },
        {
          "$type": "AttachEffect",
          "AttachEffectPosRot": {
            "CoordsOption": "ReferTarget",
            "Offset": {
              "AngleOffset": {
                "x": 0.0,
                "y": 0.0,
                "z": 0.0
              },
              "IsUseRotationXZ": true,
              "IsUseRotationY": true,
              "PositionOffset": {
                "x": 0.0,
                "y": 0.0,
                "z": 0.0
              }
            },
            "TargetOption": {
              "$type": "ConfigPosRotReferTarget",
              "AttachPoint": "RootPoint",
              "IsUseAttachPointPos": true,
              "IsUseAttachPointRotation": true,
              "OffsetReferTarget": "Self"
            }
          },
          "EffectPattern": "Eff_Device_Teller_Idle_Blue_02",
          "Target": "Self"
        },
        {
          "$type": "AttachEffect",
          "AttachEffectPosRot": {
            "CoordsOption": "ReferTarget",
            "Offset": {
              "AngleOffset": {
                "x": 0.0,
                "y": 0.0,
                "z": 0.0
              },
              "IsUseRotationXZ": true,
              "IsUseRotationY": true,
              "PositionOffset": {
                "x": 0.0,
                "y": 0.0,
                "z": 0.0
              }
            },
            "TargetOption": {
              "$type": "ConfigPosRotReferTarget",
              "AttachPoint": "BodyPoint",
              "IsUseAttachPointPos": true,
              "IsUseAttachPointRotation": true,
              "OffsetReferTarget": "Self"
            }
          },
          "EffectPattern": "Eff_Device_Teller_Idle_Blue_01",
          "Target": "Self"
        },
        {
          "$type": "AttachEffect",
          "AttachEffectPosRot": {
            "CoordsOption": "ReferTarget",
            "Offset": {
              "AngleOffset": {
                "x": 0.0,
                "y": 0.0,
                "z": 0.0
              },
              "IsUseRotationXZ": true,
              "IsUseRotationY": true,
              "PositionOffset": {
                "x": 0.0,
                "y": 0.0,
                "z": 0.0
              }
            },
            "TargetOption": {
              "$type": "ConfigPosRotReferTarget",
              "AttachPoint": "RootPoint",
              "IsUseAttachPointPos": true,
              "IsUseAttachPointRotation": true,
              "OffsetReferTarget": "Self"
            }
          },
          "EffectPattern": "Eff_Device_Teller_CoolDown",
          "Target": "Self"
        }
      ]
    },
    "CloseModifier": {
      "Duration": -1,
      "ModifierStacking": "Unique",
      "OnAdded": [
        {
          "$type": "AttachEffect",
          "AttachEffectPosRot": {
            "CoordsOption": "ReferTarget",
            "Offset": {
              "AngleOffset": {
                "x": 0.0,
                "y": 0.0,
                "z": 0.0
              },
              "IsUseRotationXZ": true,
              "IsUseRotationY": true,
              "PositionOffset": {
                "x": 0.0,
                "y": 0.0,
                "z": 0.0
              }
            },
            "TargetOption": {
              "$type": "ConfigPosRotReferTarget",
              "AttachPoint": "RootPoint",
              "IsUseAttachPointPos": true,
              "IsUseAttachPointRotation": true,
              "OffsetReferTarget": "Self"
            }
          },
          "EffectPattern": "Eff_Device_Teller_Idle_Blue_02",
          "Target": "Self"
        },
        {
          "$type": "AttachEffect",
          "AttachEffectPosRot": {
            "CoordsOption": "ReferTarget",
            "Offset": {
              "AngleOffset": {
                "x": 0.0,
                "y": 0.0,
                "z": 0.0
              },
              "IsUseRotationXZ": true,
              "IsUseRotationY": true,
              "PositionOffset": {
                "x": 0.0,
                "y": 0.0,
                "z": 0.0
              }
            },
            "TargetOption": {
              "$type": "ConfigPosRotReferTarget",
              "AttachPoint": "BodyPoint",
              "IsUseAttachPointPos": true,
              "IsUseAttachPointRotation": true,
              "OffsetReferTarget": "Self"
            }
          },
          "EffectPattern": "Eff_Device_Teller_Idle_Blue_01",
          "Target": "Self"
        },
        {
          "$type": "AttachEffect",
          "AttachEffectPosRot": {
            "CoordsOption": "ReferTarget",
            "Offset": {
              "AngleOffset": {
                "x": 0.0,
                "y": 0.0,
                "z": 0.0
              },
              "IsUseRotationXZ": true,
              "IsUseRotationY": true,
              "PositionOffset": {
                "x": 0.0,
                "y": 0.0,
                "z": 0.0
              }
            },
            "TargetOption": {
              "$type": "ConfigPosRotReferTarget",
              "AttachPoint": "RootPoint",
              "IsUseAttachPointPos": true,
              "IsUseAttachPointRotation": true,
              "OffsetReferTarget": "Self"
            }
          },
          "EffectPattern": "Eff_Device_Teller_CoolDown",
          "Target": "Self"
        }
      ]
    },
    "IdleModifier": {
      "Duration": -1,
      "ModifierStacking": "Unique",
      "OnAdded": [
        {
          "$type": "AttachEffect",
          "AttachEffectPosRot": {
            "CoordsOption": "ReferTarget",
            "Offset": {
              "AngleOffset": {
                "x": 0.0,
                "y": 0.0,
                "z": 0.0
              },
              "IsUseRotationXZ": true,
              "IsUseRotationY": true,
              "PositionOffset": {
                "x": 0.0,
                "y": 0.0,
                "z": 0.0
              }
            },
            "TargetOption": {
              "$type": "ConfigPosRotReferTarget",
              "AttachPoint": "RootPoint",
              "IsUseAttachPointPos": true,
              "IsUseAttachPointRotation": true,
              "OffsetReferTarget": "Self"
            }
          },
          "EffectPattern": "Eff_Device_Teller_Idle_Red_02",
          "Target": "Self"
        },
        {
          "$type": "AttachEffect",
          "AttachEffectPosRot": {
            "CoordsOption": "ReferTarget",
            "Offset": {
              "AngleOffset": {
                "x": 0.0,
                "y": 0.0,
                "z": 0.0
              },
              "IsUseRotationXZ": true,
              "IsUseRotationY": true,
              "PositionOffset": {
                "x": 0.0,
                "y": 0.0,
                "z": 0.0
              }
            },
            "TargetOption": {
              "$type": "ConfigPosRotReferTarget",
              "AttachPoint": "RootPoint",
              "IsUseAttachPointPos": true,
              "IsUseAttachPointRotation": true,
              "OffsetReferTarget": "Self"
            }
          },
          "EffectPattern": "Eff_Device_Teller_Scan_Start",
          "Target": "Self"
        }
      ],
      "OnRemoved": [
        {
          "$type": "CheckBankAndFireAudioEvt",
          "AudioPattern": "Stop_Teller_Scan_Loop",
          "CheckBankName": "BK_Teller"
        }
      ]
    }
  }
}